4/fifo.v
module fifo(
	input [7:0] Din, // data in
	output [7:0] Dout, // data out
	input Wen, // Write enable
	input Ren, // Read enable
	input rst, // reset
	input clk, //clock
	output reg Fempty, // Flag Empty
	output  reg Ffull // Flag Full
);
	reg [7:0] FMEM[0:15]; // FIFO memory
	reg [3:0] Wptr, Rptr; // Write Read pointer
	reg [7:0] obuf; // out buffer?
	wire [3:0] NWptr, NRptr; // Next pointer?
	
	wire [7:0] f0,f1,f2,f3,f4,f5,f6,f7,f8,f9,f10,f11,f12,f13,f14,f15;
	assign f0 = FMEM[0];
	assign f1 = FMEM[1];
	assign f2 = FMEM[2];
	assign f3 = FMEM[3];
	assign f4 = FMEM[4];
	assign f5 = FMEM[5];
	assign f6 = FMEM[6];
	assign f7 = FMEM[7];
	assign f8 = FMEM[8];
	assign f9 = FMEM[9];
	assign f10 = FMEM[10];
	assign f11 = FMEM[11];
	assign f12 = FMEM[12];
	assign f13 = FMEM[13];
	assign f14 = FMEM[14];
	assign f15 = FMEM[15];
	
	assign NWptr = Wptr+1;
	assign NRptr = Rptr+1;
	assign Dout = obuf;
	always @(posedge clk)begin
		if(rst)begin
			if(Wen==1)begin
				if(Wptr!=Rptr-1 & Ffull!=1)begin
					FMEM[Wptr] <= Din;
					Fempty <= 0;
					Wptr <= NWptr;
				end else if(Ffull!=1 & Wptr==Rptr-1) begin
					FMEM[Wptr] <= Din;
					Fempty <= 0;
					Wptr <= NWptr;
					Ffull <= 1;
				end
			end else if(Ren==1) begin
				if(Wptr-1!=Rptr & Fempty!=1) begin
					obuf <= FMEM[Rptr];
					Rptr <= NRptr;
					Ffull <= 0;
					
				end else if(Fempty!=1 & Wptr-1==Rptr)begin
					obuf <= FMEM[Rptr];
					Rptr <= NRptr;
					Ffull <= 0;
					Fempty <= 1;
				end
			end
		end else begin
			Fempty <= 1;
			Ffull <= 0;
			Wptr <= 0;
			Rptr <= 0;
		end
	end



endmodule

4/simfifo2.v
`timescale 1ns/1ps
module top;
   reg[7:0] Din;
   wire [7:0] Dout;
   reg ck, rst, Wen, Ren, flag;
   wire Fempty, Ffull;

/// For test purposes
   reg [7:0] FMEM[0:15];
   reg [3:0] Wptr, Rptr;
   reg 	     Fempty0, Ffull0;
   reg [7:0] obuf;
   wire [3:0] NWptr, NRptr;
   
   assign NWptr = Wptr + 1;
   assign NRptr = Rptr + 1;
/// For test purposes

   
   fifo fifo( Din, Dout, Wen, Ren, rst, ck, Fempty, Ffull );

   initial begin
	ck = 0;
	rst = 1;
	$dumpfile( "fifo.vcd" );
	$dumpvars;
	#20 rst = 0;
	#50 rst = 1;
	#10000 
	  $display( "OK\n" );
      $finish;
   end

   always @(negedge ck)begin
     flag = $random;
     if( flag == 1 )begin
	Wen <= 1;
	Ren <= 0;
	Din = $random;
     end else begin
	Wen <= 0;
	Ren <= 1;
     end
   end

   always #10 ck <= ~ck;


   
   always @(posedge ck) begin
      if( Fempty0 != Fempty || Ffull0 != Ffull || obuf != Dout ) begin
	 $finish;
      end
   end

   always @(posedge ck) begin
      if( !rst ) begin
	 Wptr <= 0;
	 Rptr <= 0;
	 Fempty0 <= 1;
	 Ffull0 <= 0;
      end else begin
	 if( Ren == 1 && Fempty0 != 1 ) begin
	    obuf <= FMEM[Rptr];
	    Rptr <= NRptr;
	    Ffull0 <= 0;
	    if( NRptr == Wptr ) Fempty0 <= 1;
	    else Fempty0 <= 0;
	 end
	 if( Wen == 1 && Ffull0 != 1 ) begin
	    FMEM[Wptr] <= Din;
	    Wptr <= Wptr + 1;
	    Fempty0 <= 0;
	    if( NWptr == Rptr ) Ffull0 <= 1;
	    else Ffull0 <= 0;
	    
	 end
      end
   end
      
endmodule

4/fifo.vcd
$date
	Fri Apr 29 02:28:19 2022
$end
$version
	Icarus Verilog
$end
$timescale
	1ps
$end
$scope module top $end
$var wire 4 ! NWptr [3:0] $end
$var wire 4 " NRptr [3:0] $end
$var wire 1 # Ffull $end
$var wire 1 $ Fempty $end
$var wire 8 % Dout [7:0] $end
$var reg 8 & Din [7:0] $end
$var reg 1 ' Fempty0 $end
$var reg 1 ( Ffull0 $end
$var reg 1 ) Ren $end
$var reg 4 * Rptr [3:0] $end
$var reg 1 + Wen $end
$var reg 4 , Wptr [3:0] $end
$var reg 1 - ck $end
$var reg 1 . flag $end
$var reg 8 / obuf [7:0] $end
$var reg 1 0 rst $end
$scope module fifo $end
$var wire 8 1 Din [7:0] $end
$var wire 8 2 Dout [7:0] $end
$var wire 1 ) Ren $end
$var wire 1 + Wen $end
$var wire 1 - clk $end
$var wire 8 3 f0 [7:0] $end
$var wire 8 4 f1 [7:0] $end
$var wire 8 5 f10 [7:0] $end
$var wire 8 6 f11 [7:0] $end
$var wire 8 7 f12 [7:0] $end
$var wire 8 8 f13 [7:0] $end
$var wire 8 9 f14 [7:0] $end
$var wire 8 : f15 [7:0] $end
$var wire 8 ; f2 [7:0] $end
$var wire 8 < f3 [7:0] $end
$var wire 8 = f4 [7:0] $end
$var wire 8 > f5 [7:0] $end
$var wire 8 ? f6 [7:0] $end
$var wire 8 @ f7 [7:0] $end
$var wire 8 A f8 [7:0] $end
$var wire 8 B f9 [7:0] $end
$var wire 1 0 rst $end
$var wire 4 C NWptr [3:0] $end
$var wire 4 D NRptr [3:0] $end
$var reg 1 $ Fempty $end
$var reg 1 # Ffull $end
$var reg 4 E Rptr [3:0] $end
$var reg 4 F Wptr [3:0] $end
$var reg 8 G obuf [7:0] $end
$upscope $end
$upscope $end
$enddefinitions $end
#0
$dumpvars
bx G
bx F
bx E
bx D
bx C
bx B
bx A
bx @
bx ?
bx >
bx =
bx <
bx ;
bx :
bx 9
bx 8
bx 7
bx 6
bx 5
bx 4
bx 3
bx 2
bx 1
10
bx /
x.
0-
bx ,
x+
bx *
x)
x(
x'
bx &
bx %
x$
x#
bx "
bx !
$end
#10000
1-
#20000
1)
0+
0.
0-
00
#30000
0(
1'
b1 "
b0 *
b1 !
b0 ,
b1 D
b0 E
b1 C
b0 F
0#
1$
1-
#40000
0)
1+
b1001 &
b1001 1
1.
0-
#50000
1-
#60000
b1101 &
b1101 1
0-
#70000
0'
b10 !
b1 ,
b10 C
b1 F
0$
b1101 3
1-
10
#80000
b1100101 &
b1100101 1
0-
#90000
b11 C
b10 F
b1100101 4
b11 !
b10 ,
1-
#100000
1)
0+
0.
0-
#110000
b10 "
b1 *
b1101 /
b10 D
b1 E
b1101 %
b1101 2
b1101 G
1-
#120000
0)
1+
b1101 &
b1101 1
1.
0-
#130000
b100 C
b11 F
b1101 ;
b100 !
b11 ,
1-
#140000
1)
0+
0.
0-
#150000
b11 "
b10 *
b1100101 /
b11 D
b10 E
b1100101 %
b1100101 2
b1100101 G
1-
#160000
0)
1+
b11101101 &
b11101101 1
1.
0-
#170000
b101 C
b100 F
b11101101 <
b101 !
b100 ,
1-
#180000
1)
0+
0.
0-
#190000
b100 "
b11 *
b1101 /
b100 D
b11 E
b1101 %
b1101 2
b1101 G
1-
#200000
0)
1+
b11000110 &
b11000110 1
1.
0-
#210000
b110 C
b101 F
b11000110 =
b110 !
b101 ,
1-
#220000
b10101010 &
b10101010 1
0-
#230000
b111 !
b110 ,
b111 C
b110 F
b10101010 >
1-
#240000
b1110111 &
b1110111 1
0-
#250000
b1000 C
b111 F
b1110111 ?
b1000 !
b111 ,
1-
#260000
1)
0+
0.
0-
#270000
b101 "
b100 *
b11101101 /
b101 D
b100 E
b11101101 %
b11101101 2
b11101101 G
1-
#280000
0)
1+
b11110010 &
b11110010 1
1.
0-
#290000
b1001 C
b1000 F
b11110010 @
b1001 !
b1000 ,
1-
#300000
1)
0+
0.
0-
#310000
b110 "
b101 *
b11000110 /
b110 D
b101 E
b11000110 %
b11000110 2
b11000110 G
1-
#320000
0-
#330000
b111 D
b110 E
b10101010 %
b10101010 2
b10101010 G
b111 "
b110 *
b10101010 /
1-
#340000
0)
1+
b1011100 &
b1011100 1
1.
0-
#350000
b1010 !
b1001 ,
b1010 C
b1001 F
b1011100 A
1-
#360000
b101101 &
b101101 1
0-
#370000
b1011 C
b1010 F
b101101 B
b1011 !
b1010 ,
1-
#380000
b1100011 &
b1100011 1
0-
#390000
b1100 !
b1011 ,
b1100 C
b1011 F
b1100011 5
1-
#400000
1)
0+
0.
0-
#410000
b1000 D
b111 E
b1110111 %
b1110111 2
b1110111 G
b1000 "
b111 *
b1110111 /
1-
#420000
0-
#430000
b1001 "
b1000 *
b11110010 /
b1001 D
b1000 E
b11110010 %
b11110010 2
b11110010 G
1-
#440000
0-
#450000
b1010 D
b1001 E
b1011100 %
b1011100 2
b1011100 G
b1010 "
b1001 *
b1011100 /
1-
#460000
0-
#470000
b1011 "
b1010 *
b101101 /
b1011 D
b1010 E
b101101 %
b101101 2
b101101 G
1-
#480000
0)
1+
b10010110 &
b10010110 1
1.
0-
#490000
b1101 C
b1100 F
b10010110 6
b1101 !
b1100 ,
1-
#500000
b1101 &
b1101 1
0-
#510000
b1110 !
b1101 ,
b1110 C
b1101 F
b1101 7
1-
#520000
b1101011 &
b1101011 1
0-
#530000
b1111 C
b1110 F
b1101011 8
b1111 !
b1110 ,
1-
#540000
b10 &
b10 1
0-
#550000
b0 !
b1111 ,
b0 C
b1111 F
b10 9
1-
#560000
1)
0+
0.
0-
#570000
b1100 D
b1011 E
b1100011 %
b1100011 2
b1100011 G
b1100 "
b1011 *
b1100011 /
1-
#580000
0)
1+
b11001111 &
b11001111 1
1.
0-
#590000
b1 !
b0 ,
b1 C
b0 F
b11001111 :
1-
#600000
b1010 &
b1010 1
0-
#610000
b10 C
b1 F
b1010 3
b10 !
b1 ,
1-
#620000
1)
0+
0.
0-
#630000
b1101 "
b1100 *
b10010110 /
b1101 D
b1100 E
b10010110 %
b10010110 2
b10010110 G
1-
#640000
0-
#650000
b1110 D
b1101 E
b1101 %
b1101 2
b1101 G
b1110 "
b1101 *
b1101 /
1-
#660000
0-
#670000
b1111 "
b1110 *
b1101011 /
b1111 D
b1110 E
b1101011 %
b1101011 2
b1101011 G
1-
#680000
0-
#690000
b0 D
b1111 E
b10 %
b10 2
b10 G
b0 "
b1111 *
b10 /
1-
#700000
0)
1+
b11011000 &
b11011000 1
1.
0-
#710000
b11 !
b10 ,
b11 C
b10 F
b11011000 4
1-
#720000
1)
0+
0.
0-
#730000
b1 D
b0 E
b11001111 %
b11001111 2
b11001111 G
b1 "
b0 *
b11001111 /
1-
#740000
0)
1+
b11101011 &
b11101011 1
1.
0-
#750000
b100 !
b11 ,
b100 C
b11 F
b11101011 ;
1-
#760000
1)
0+
0.
0-
#770000
b10 D
b1 E
b1010 %
b1010 2
b1010 G
b10 "
b1 *
b1010 /
1-
#780000
0-
#790000
b11 "
b10 *
b11011000 /
b11 D
b10 E
b11011000 %
b11011000 2
b11011000 G
1-
#800000
0-
#810000
1$
b100 D
b11 E
b11101011 %
b11101011 2
b11101011 G
1'
b100 "
b11 *
b11101011 /
1-
#820000
0-
#830000
1-
#840000
0-
#850000
1-
#860000
0)
1+
b1110001 &
b1110001 1
1.
0-
#870000
0'
b101 !
b100 ,
b101 C
b100 F
0$
b1110001 <
1-
#880000
b1001111 &
b1001111 1
0-
#890000
b110 C
b101 F
b1001111 =
b110 !
b101 ,
1-
#900000
b111010 &
b111010 1
0-
#910000
b111 !
b110 ,
b111 C
b110 F
b111010 >
1-
#920000
1)
0+
0.
0-
#930000
b101 D
b100 E
b1110001 %
b1110001 2
b1110001 G
b101 "
b100 *
b1110001 /
1-
#940000
0)
1+
b11110001 &
b11110001 1
1.
0-
#950000
b1000 !
b111 ,
b1000 C
b111 F
b11110001 ?
1-
#960000
b1100010 &
b1100010 1
0-
#970000
b1001 C
b1000 F
b1100010 @
b1001 !
b1000 ,
1-
#980000
1)
0+
0.
0-
#990000
b110 "
b101 *
b1001111 /
b110 D
b101 E
b1001111 %
b1001111 2
b1001111 G
1-
#1000000
0)
1+
b10001111 &
b10001111 1
1.
0-
#1010000
b1010 C
b1001 F
b10001111 A
b1010 !
b1001 ,
1-
#1020000
1)
0+
0.
0-
#1030000
b111 "
b110 *
b111010 /
b111 D
b110 E
b111010 %
b111010 2
b111010 G
1-
#1040000
0)
1+
b10011111 &
b10011111 1
1.
0-
#1050000
b1011 C
b1010 F
b10011111 B
b1011 !
b1010 ,
1-
#1060000
1)
0+
0.
0-
#1070000
b1000 "
b111 *
b11110001 /
b1000 D
b111 E
b11110001 %
b11110001 2
b11110001 G
1-
#1080000
0)
1+
b10001001 &
b10001001 1
1.
0-
#1090000
b1100 C
b1011 F
b10001001 5
b1100 !
b1011 ,
1-
#1100000
b11010000 &
b11010000 1
0-
#1110000
b1101 !
b1100 ,
b1101 C
b1100 F
b11010000 6
1-
#1120000
b1010001 &
b1010001 1
0-
#1130000
b1110 C
b1101 F
b1010001 7
b1110 !
b1101 ,
1-
#1140000
1)
0+
0.
0-
#1150000
b1001 "
b1000 *
b1100010 /
b1001 D
b1000 E
b1100010 %
b1100010 2
b1100010 G
1-
#1160000
0-
#1170000
b1010 D
b1001 E
b10001111 %
b10001111 2
b10001111 G
b1010 "
b1001 *
b10001111 /
1-
#1180000
0-
#1190000
b1011 "
b1010 *
b10011111 /
b1011 D
b1010 E
b10011111 %
b10011111 2
b10011111 G
1-
#1200000
0-
#1210000
b1100 D
b1011 E
b10001001 %
b10001001 2
b10001001 G
b1100 "
b1011 *
b10001001 /
1-
#1220000
0)
1+
b111101 &
b111101 1
1.
0-
#1230000
b1111 !
b1110 ,
b1111 C
b1110 F
b111101 8
1-
#1240000
1)
0+
0.
0-
#1250000
b1101 D
b1100 E
b11010000 %
b11010000 2
b11010000 G
b1101 "
b1100 *
b11010000 /
1-
#1260000
0-
#1270000
b1110 "
b1101 *
b1010001 /
b1110 D
b1101 E
b1010001 %
b1010001 2
b1010001 G
1-
#1280000
0)
1+
b111001 &
b111001 1
1.
0-
#1290000
b0 C
b1111 F
b111001 9
b0 !
b1111 ,
1-
#1300000
b11010011 &
b11010011 1
0-
#1310000
b1 !
b0 ,
b1 C
b0 F
b11010011 :
1-
#1320000
b1111000 &
b1111000 1
0-
#1330000
b10 C
b1 F
b1111000 3
b10 !
b1 ,
1-
#1340000
b1001001 &
b1001001 1
0-
#1350000
b11 !
b10 ,
b11 C
b10 F
b1001001 4
1-
#1360000
b101010 &
b101010 1
0-
#1370000
b100 C
b11 F
b101010 ;
b100 !
b11 ,
1-
#1380000
1)
0+
0.
0-
#1390000
b1111 "
b1110 *
b111101 /
b1111 D
b1110 E
b111101 %
b111101 2
b111101 G
1-
#1400000
0-
#1410000
b0 D
b1111 E
b111001 %
b111001 2
b111001 G
b0 "
b1111 *
b111001 /
1-
#1420000
0-
#1430000
b1 "
b0 *
b11010011 /
b1 D
b0 E
b11010011 %
b11010011 2
b11010011 G
1-
#1440000
0-
#1450000
b10 D
b1 E
b1111000 %
b1111000 2
b1111000 G
b10 "
b1 *
b1111000 /
1-
#1460000
0-
#1470000
b11 "
b10 *
b1001001 /
b11 D
b10 E
b1001001 %
b1001001 2
b1001001 G
1-
#1480000
0-
#1490000
1$
b100 D
b11 E
b101010 %
b101010 2
b101010 G
1'
b100 "
b11 *
b101010 /
1-
#1500000
0)
1+
b10100011 &
b10100011 1
1.
0-
#1510000
0'
b101 !
b100 ,
b101 C
b100 F
0$
b10100011 <
1-
#1520000
b10110011 &
b10110011 1
0-
#1530000
b110 C
b101 F
b10110011 =
b110 !
b101 ,
1-
#1540000
b1000100 &
b1000100 1
0-
#1550000
b111 !
b110 ,
b111 C
b110 F
b1000100 >
1-
#1560000
b11001011 &
b11001011 1
0-
#1570000
b1000 C
b111 F
b11001011 ?
b1000 !
b111 ,
1-
#1580000
1)
0+
0.
0-
#1590000
b101 "
b100 *
b10100011 /
b101 D
b100 E
b10100011 %
b10100011 2
b10100011 G
1-
#1600000
0-
#1610000
b110 D
b101 E
b10110011 %
b10110011 2
b10110011 G
b110 "
b101 *
b10110011 /
1-
#1620000
0)
1+
b11101101 &
b11101101 1
1.
0-
#1630000
b1001 !
b1000 ,
b1001 C
b1000 F
b11101101 @
1-
#1640000
1)
0+
0.
0-
#1650000
b111 D
b110 E
b1000100 %
b1000100 2
b1000100 G
b111 "
b110 *
b1000100 /
1-
#1660000
0)
1+
b10110101 &
b10110101 1
1.
0-
#1670000
b1010 !
b1001 ,
b1010 C
b1001 F
b10110101 A
1-
#1680000
b1111001 &
b1111001 1
0-
#1690000
b1011 C
b1010 F
b1111001 B
b1011 !
b1010 ,
1-
#1700000
1)
0+
0.
0-
#1710000
b1000 "
b111 *
b11001011 /
b1000 D
b111 E
b11001011 %
b11001011 2
b11001011 G
1-
#1720000
0-
#1730000
b1001 D
b1000 E
b11101101 %
b11101101 2
b11101101 G
b1001 "
b1000 *
b11101101 /
1-
#1740000
0-
#1750000
b1010 "
b1001 *
b10110101 /
b1010 D
b1001 E
b10110101 %
b10110101 2
b10110101 G
1-
#1760000
0)
1+
b1110 &
b1110 1
1.
0-
#1770000
b1100 C
b1011 F
b1110 5
b1100 !
b1011 ,
1-
#1780000
1)
0+
0.
0-
#1790000
b1011 "
b1010 *
b1111001 /
b1011 D
b1010 E
b1111001 %
b1111001 2
b1111001 G
1-
#1800000
0-
#1810000
1$
b1100 D
b1011 E
b1110 %
b1110 2
b1110 G
1'
b1100 "
b1011 *
b1110 /
1-
#1820000
0)
1+
b11000011 &
b11000011 1
1.
0-
#1830000
0'
b1101 !
b1100 ,
b1101 C
b1100 F
0$
b11000011 6
1-
#1840000
1)
0+
0.
0-
#1850000
1$
b1101 D
b1100 E
b11000011 %
b11000011 2
b11000011 G
1'
b1101 "
b1100 *
b11000011 /
1-
#1860000
0-
#1870000
1-
#1880000
0)
1+
b1010 &
b1010 1
1.
0-
#1890000
b1110 C
b1101 F
0$
b1010 7
0'
b1110 !
b1101 ,
1-
#1900000
1)
0+
0.
0-
#1910000
1'
b1110 "
b1101 *
b1010 /
1$
b1110 D
b1101 E
b1010 %
b1010 2
b1010 G
1-
#1920000
0-
#1930000
1-
#1940000
0)
1+
b10111000 &
b10111000 1
1.
0-
#1950000
0'
b1111 !
b1110 ,
b1111 C
b1110 F
0$
b10111000 8
1-
#1960000
1)
0+
0.
0-
#1970000
1$
b1111 D
b1110 E
b10111000 %
b10111000 2
b10111000 G
1'
b1111 "
b1110 *
b10111000 /
1-
#1980000
0)
1+
b100 &
b100 1
1.
0-
#1990000
0'
b0 !
b1111 ,
b0 C
b1111 F
0$
b100 9
1-
#2000000
b11011011 &
b11011011 1
0-
#2010000
b1 C
b0 F
b11011011 :
b1 !
b0 ,
1-
#2020000
b11011001 &
b11011001 1
0-
#2030000
b10 !
b1 ,
b10 C
b1 F
b11011001 3
1-
#2040000
b1110110 &
b1110110 1
0-
#2050000
b11 C
b10 F
b1110110 4
b11 !
b10 ,
1-
#2060000
1)
0+
0.
0-
#2070000
b0 "
b1111 *
b100 /
b0 D
b1111 E
b100 %
b100 2
b100 G
1-
#2080000
0-
#2090000
b1 D
b0 E
b11011011 %
b11011011 2
b11011011 G
b1 "
b0 *
b11011011 /
1-
#2100000
0)
1+
b1000110 &
b1000110 1
1.
0-
#2110000
b100 !
b11 ,
b100 C
b11 F
b1000110 ;
1-
#2120000
1)
0+
0.
0-
#2130000
b10 D
b1 E
b11011001 %
b11011001 2
b11011001 G
b10 "
b1 *
b11011001 /
1-
#2140000
0)
1+
b1101001 &
b1101001 1
1.
0-
#2150000
b101 !
b100 ,
b101 C
b100 F
b1101001 <
1-
#2160000
1)
0+
0.
0-
#2170000
b11 D
b10 E
b1110110 %
b1110110 2
b1110110 G
b11 "
b10 *
b1110110 /
1-
#2180000
0-
#2190000
b100 "
b11 *
b1000110 /
b100 D
b11 E
b1000110 %
b1000110 2
b1000110 G
1-
#2200000
0-
#2210000
1$
b101 D
b100 E
b1101001 %
b1101001 2
b1101001 G
1'
b101 "
b100 *
b1101001 /
1-
#2220000
0)
1+
b11000111 &
b11000111 1
1.
0-
#2230000
0'
b110 !
b101 ,
b110 C
b101 F
0$
b11000111 =
1-
#2240000
1)
0+
0.
0-
#2250000
1$
b110 D
b101 E
b11000111 %
b11000111 2
b11000111 G
1'
b110 "
b101 *
b11000111 /
1-
#2260000
0-
#2270000
1-
#2280000
0-
#2290000
1-
#2300000
0)
1+
b101001 &
b101001 1
1.
0-
#2310000
0'
b111 !
b110 ,
b111 C
b110 F
0$
b101001 >
1-
#2320000
1)
0+
0.
0-
#2330000
1$
b111 D
b110 E
b101001 %
b101001 2
b101001 G
1'
b111 "
b110 *
b101001 /
1-
#2340000
0-
#2350000
1-
#2360000
0-
#2370000
1-
#2380000
0)
1+
b1100110 &
b1100110 1
1.
0-
#2390000
0'
b1000 !
b111 ,
b1000 C
b111 F
0$
b1100110 ?
1-
#2400000
1)
0+
0.
0-
#2410000
1$
b1000 D
b111 E
b1100110 %
b1100110 2
b1100110 G
1'
b1000 "
b111 *
b1100110 /
1-
#2420000
0)
1+
b10111010 &
b10111010 1
1.
0-
#2430000
0'
b1001 !
b1000 ,
b1001 C
b1000 F
0$
b10111010 @
1-
#2440000
1)
0+
0.
0-
#2450000
1$
b1001 D
b1000 E
b10111010 %
b10111010 2
b10111010 G
1'
b1001 "
b1000 *
b10111010 /
1-
#2460000
0-
#2470000
1-
#2480000
0)
1+
b11010 &
b11010 1
1.
0-
#2490000
b1010 C
b1001 F
0$
b11010 A
0'
b1010 !
b1001 ,
1-
#2500000
b110111 &
b110111 1
0-
#2510000
b1011 !
b1010 ,
b1011 C
b1010 F
b110111 B
1-
#2520000
1)
0+
0.
0-
#2530000
b1010 D
b1001 E
b11010 %
b11010 2
b11010 G
b1010 "
b1001 *
b11010 /
1-
#2540000
0-
#2550000
1'
b1011 "
b1010 *
b110111 /
1$
b1011 D
b1010 E
b110111 %
b110111 2
b110111 G
1-
#2560000
0-
#2570000
1-
#2580000
0-
#2590000
1-
#2600000
0)
1+
b11011100 &
b11011100 1
1.
0-
#2610000
b1100 C
b1011 F
0$
b11011100 5
0'
b1100 !
b1011 ,
1-
#2620000
1)
0+
0.
0-
#2630000
1'
b1100 "
b1011 *
b11011100 /
1$
b1100 D
b1011 E
b11011100 %
b11011100 2
b11011100 G
1-
#2640000
0-
#2650000
1-
#2660000
0-
#2670000
1-
#2680000
0)
1+
b11001111 &
b11001111 1
1.
0-
#2690000
b1101 C
b1100 F
0$
b11001111 6
0'
b1101 !
b1100 ,
1-
#2700000
b11111010 &
b11111010 1
0-
#2710000
b1110 !
b1101 ,
b1110 C
b1101 F
b11111010 7
1-
#2720000
b10111 &
b10111 1
0-
#2730000
b1111 C
b1110 F
b10111 8
b1111 !
b1110 ,
1-
#2740000
b10000110 &
b10000110 1
0-
#2750000
b0 !
b1111 ,
b0 C
b1111 F
b10000110 9
1-
#2760000
1)
0+
0.
0-
#2770000
b1101 D
b1100 E
b11001111 %
b11001111 2
b11001111 G
b1101 "
b1100 *
b11001111 /
1-
#2780000
0)
1+
b110101 &
b110101 1
1.
0-
#2790000
b1 !
b0 ,
b1 C
b0 F
b110101 :
1-
#2800000
b11000001 &
b11000001 1
0-
#2810000
b10 C
b1 F
b11000001 3
b10 !
b1 ,
1-
#2820000
b10011000 &
b10011000 1
0-
#2830000
b11 !
b10 ,
b11 C
b10 F
b10011000 4
1-
#2840000
b1110011 &
b1110011 1
0-
#2850000
b100 C
b11 F
b1110011 ;
b100 !
b11 ,
1-
#2860000
1)
0+
0.
0-
#2870000
b1110 "
b1101 *
b11111010 /
b1110 D
b1101 E
b11111010 %
b11111010 2
b11111010 G
1-
#2880000
0-
#2890000
b1111 D
b1110 E
b10111 %
b10111 2
b10111 G
b1111 "
b1110 *
b10111 /
1-
#2900000
0-
#2910000
b0 "
b1111 *
b10000110 /
b0 D
b1111 E
b10000110 %
b10000110 2
b10000110 G
1-
#2920000
0-
#2930000
b1 D
b0 E
b110101 %
b110101 2
b110101 G
b1 "
b0 *
b110101 /
1-
#2940000
0)
1+
b10100001 &
b10100001 1
1.
0-
#2950000
b101 !
b100 ,
b101 C
b100 F
b10100001 <
1-
#2960000
1)
0+
0.
0-
#2970000
b10 D
b1 E
b11000001 %
b11000001 2
b11000001 G
b10 "
b1 *
b11000001 /
1-
#2980000
0-
#2990000
b11 "
b10 *
b10011000 /
b11 D
b10 E
b10011000 %
b10011000 2
b10011000 G
1-
#3000000
0)
1+
b101010 &
b101010 1
1.
0-
#3010000
b110 C
b101 F
b101010 =
b110 !
b101 ,
1-
#3020000
1)
0+
0.
0-
#3030000
b100 "
b11 *
b1110011 /
b100 D
b11 E
b1110011 %
b1110011 2
b1110011 G
1-
#3040000
0)
1+
b10011110 &
b10011110 1
1.
0-
#3050000
b111 C
b110 F
b10011110 >
b111 !
b110 ,
1-
#3060000
1)
0+
0.
0-
#3070000
b101 "
b100 *
b10100001 /
b101 D
b100 E
b10100001 %
b10100001 2
b10100001 G
1-
#3080000
0)
1+
b11001000 &
b11001000 1
1.
0-
#3090000
b1000 C
b111 F
b11001000 ?
b1000 !
b111 ,
1-
#3100000
1)
0+
0.
0-
#3110000
b110 "
b101 *
b101010 /
b110 D
b101 E
b101010 %
b101010 2
b101010 G
1-
#3120000
0)
1+
b1101011 &
b1101011 1
1.
0-
#3130000
b1001 C
b1000 F
b1101011 @
b1001 !
b1000 ,
1-
#3140000
b10110110 &
b10110110 1
0-
#3150000
b1010 !
b1001 ,
b1010 C
b1001 F
b10110110 A
1-
#3160000
1)
0+
0.
0-
#3170000
b111 D
b110 E
b10011110 %
b10011110 2
b10011110 G
b111 "
b110 *
b10011110 /
1-
#3180000
0-
#3190000
b1000 "
b111 *
b11001000 /
b1000 D
b111 E
b11001000 %
b11001000 2
b11001000 G
1-
#3200000
0)
1+
b10010010 &
b10010010 1
1.
0-
#3210000
b1011 C
b1010 F
b10010010 B
b1011 !
b1010 ,
1-
#3220000
1)
0+
0.
0-
#3230000
b1001 "
b1000 *
b1101011 /
b1001 D
b1000 E
b1101011 %
b1101011 2
b1101011 G
1-
#3240000
0)
1+
b10000110 &
b10000110 1
1.
0-
#3250000
b1100 C
b1011 F
b10000110 5
b1100 !
b1011 ,
1-
#3260000
1)
0+
0.
0-
#3270000
b1010 "
b1001 *
b10110110 /
b1010 D
b1001 E
b10110110 %
b10110110 2
b10110110 G
1-
#3280000
0-
#3290000
b1011 D
b1010 E
b10010010 %
b10010010 2
b10010010 G
b1011 "
b1010 *
b10010010 /
1-
#3300000
0-
#3310000
1'
b1100 "
b1011 *
b10000110 /
1$
b1100 D
b1011 E
b10000110 %
b10000110 2
b10000110 G
1-
#3320000
0)
1+
b10000100 &
b10000100 1
1.
0-
#3330000
b1101 C
b1100 F
0$
b10000100 6
0'
b1101 !
b1100 ,
1-
#3340000
1)
0+
0.
0-
#3350000
1'
b1101 "
b1100 *
b10000100 /
1$
b1101 D
b1100 E
b10000100 %
b10000100 2
b10000100 G
1-
#3360000
0-
#3370000
1-
#3380000
0)
1+
b10100001 &
b10100001 1
1.
0-
#3390000
0'
b1110 !
b1101 ,
b1110 C
b1101 F
0$
b10100001 7
1-
#3400000
1)
0+
0.
0-
#3410000
1$
b1110 D
b1101 E
b10100001 %
b10100001 2
b10100001 G
1'
b1110 "
b1101 *
b10100001 /
1-
#3420000
0)
1+
b1011 &
b1011 1
1.
0-
#3430000
0'
b1111 !
b1110 ,
b1111 C
b1110 F
0$
b1011 8
1-
#3440000
b11001001 &
b11001001 1
0-
#3450000
b0 C
b1111 F
b11001001 9
b0 !
b1111 ,
1-
#3460000
1)
0+
0.
0-
#3470000
b1111 "
b1110 *
b1011 /
b1111 D
b1110 E
b1011 %
b1011 2
b1011 G
1-
#3480000
0)
1+
b10001111 &
b10001111 1
1.
0-
#3490000
b1 C
b0 F
b10001111 :
b1 !
b0 ,
1-
#3500000
b10001000 &
b10001000 1
0-
#3510000
b10 !
b1 ,
b10 C
b1 F
b10001000 3
1-
#3520000
1)
0+
0.
0-
#3530000
b0 D
b1111 E
b11001001 %
b11001001 2
b11001001 G
b0 "
b1111 *
b11001001 /
1-
#3540000
0)
1+
b10010010 &
b10010010 1
1.
0-
#3550000
b11 !
b10 ,
b11 C
b10 F
b10010010 4
1-
#3560000
1)
0+
0.
0-
#3570000
b1 D
b0 E
b10001111 %
b10001111 2
b10001111 G
b1 "
b0 *
b10001111 /
1-
#3580000
0)
1+
b1001011 &
b1001011 1
1.
0-
#3590000
b100 !
b11 ,
b100 C
b11 F
b1001011 ;
1-
#3600000
1)
0+
0.
0-
#3610000
b10 D
b1 E
b10001000 %
b10001000 2
b10001000 G
b10 "
b1 *
b10001000 /
1-
#3620000
0-
#3630000
b11 "
b10 *
b10010010 /
b11 D
b10 E
b10010010 %
b10010010 2
b10010010 G
1-
#3640000
0)
1+
b11101100 &
b11101100 1
1.
0-
#3650000
b101 C
b100 F
b11101100 <
b101 !
b100 ,
1-
#3660000
1)
0+
0.
0-
#3670000
b100 "
b11 *
b1001011 /
b100 D
b11 E
b1001011 %
b1001011 2
b1001011 G
1-
#3680000
0)
1+
b10000110 &
b10000110 1
1.
0-
#3690000
b110 C
b101 F
b10000110 =
b110 !
b101 ,
1-
#3700000
b111011 &
b111011 1
0-
#3710000
b111 !
b110 ,
b111 C
b110 F
b111011 >
1-
#3720000
1)
0+
0.
0-
#3730000
b101 D
b100 E
b11101100 %
b11101100 2
b11101100 G
b101 "
b100 *
b11101100 /
1-
#3740000
0)
1+
b1010110 &
b1010110 1
1.
0-
#3750000
b1000 !
b111 ,
b1000 C
b111 F
b1010110 ?
1-
#3760000
b11100010 &
b11100010 1
0-
#3770000
b1001 C
b1000 F
b11100010 @
b1001 !
b1000 ,
1-
#3780000
1)
0+
0.
0-
