5/cpu.v
module CPU(
    input CK,
    input RST,
    output [15:0] IA,
    input [15:0] ID,
    output [15:0] DA,
    inout [15:0] DD,
    output reg RW);

reg [1:0] STAGE;
reg [15:0] RF[0:14], PC, PCI, PCC, FUA, FUB, FUC, LSUA, LSUB, LSUC, INST;
wire [3:0] OPCODE, OPR1, OPR2, OPR3;
wire [15:0] ABUS, BBUS, CBUS;
wire [7:0] IMM;
reg FLAG;

assign IA = PC;
assign OPCODE = INST[15:12];
assign OPR1 = INST[11:8];
assign OPR2 = INST[7:4];
assign OPR3 = INST[3:0];
assign IMM = INST[7:0];
assign ABUS = (OPR2==0 ? 0:RF[OPR2]);
assign BBUS = (OPR3==0 ? 0:RF[OPR3]);
assign DD = (RW==0 ? LSUA:'bZ);
assign DA = LSUB;
assign CBUS = (OPCODE[3]==0 ? FUC:(OPCODE[3:1]=='b101 ? LSUC:(OPCODE=='b1100 ? {8'b0,IMM}:OPCODE=='b1000 ? PCC:'bZ)));

always @(posedge CK)begin
    if(RST==1)begin
        PC <= 0;
        STAGE <= 0;
        RW <= 1;
    end else begin
        if(STAGE==0)begin
            STAGE <= 1;
            INST <= ID;
        end else if(STAGE==1)begin
            STAGE <= 2;
            if(OPCODE[3]==0)begin
                FUA <= ABUS; FUB <= BBUS;
            end
            if(OPCODE[2:1]=='b01)begin
                LSUA <= ABUS; LSUB <= BBUS;
            end
            if(OPCODE[3:0]=='b1000 || (OPCODE[3:0]=='b1001 && FLAG==1))begin
                PCI <= BBUS;
            end else begin
                PCI <= PC+1;
            end
        end else if(STAGE==2)begin
            STAGE <= 3;
            if(OPCODE[3]==0)begin
                case(OPCODE[2:0])
                'b000: FUC <= FUA+FUB;
                'b001: FUC <= FUA-FUB;
                'b010: FUC <= FUA>>FUB;
                'b011: FUC <= FUA<<FUB;
                'b100: FUC <= FUA|FUB;
                'b101: FUC <= FUA&FUB;
                'b110: FUC <= ~FUA;
                'b111: FUC <= FUA^FUB;
                endcase
            end
            if(OPCODE[3:1]=='b101)begin
                if(OPCODE[0]==0)begin
                    RW <= 0;
                end else begin
                    RW <= 1; LSUC <= DD;
                end
            end
            if(OPCODE[3:0]=='b1000)begin
                PCC <= PC+1;
            end
        end else if(STAGE==3)begin
            STAGE <= 0;
            RF[OPR1] <= CBUS;
            PC <= PCI;
            if(OPCODE[3]==0)begin
                if(CBUS==0)begin
                    FLAG <= 1;
                end else begin
                    FLAG <= 0;
                end
            end
        end
    end
end

endmodule

5/simcpu4.v
module simcpu;
reg CK, RST;
wire RW;
wire [15:0] IA, DA, DD;
reg [15:0] ID, DDi;
reg [15:0] IMEM [0:127], DMEM[0:127];

	CPU c(CK,RST,IA,ID,DA,DD,RW);

   assign DD = ((RW == 1) ? DDi : 'b Z);

initial begin
   $dumpfile("cpu.vcd");
   $dumpvars;
	CK = 0;
	RST = 0;
#5	RST = 1;
#100	RST = 0;
	
        #10000 $finish;
end

always @(negedge CK) begin
   if( DA == 'b 0 && DD == 'b 0100 && RW == 0 ) begin
      $display( "OK" );
      $finish;
   end
end

always @(negedge CK) begin
	ID = IMEM[IA];
end

always @(negedge CK) begin
   if( RW == 1 ) DDi = DMEM[DA];
   else DMEM[DA] = DD;
   $display("%b %b %b %b %b %b %b %b %b %b %b %b %b %b ",
   DMEM[0],DMEM[1],DMEM[2],DMEM[3],DMEM[4],DMEM[5],DMEM[6],DMEM[7],DMEM[8],DMEM[9],DMEM[10],DMEM[11],DMEM[12],DMEM[13]);
end

initial begin
   DMEM[0] = 4;
   DMEM[1] = 2;
   //R0, R1, R2 is used
IMEM[0] = 'b 1100_0000_0000_0100;
IMEM[1] = 'b 1100_0001_0000_0010;
IMEM[2] = 'b 1100_0011_0000_0000; // R3 = 0 answer
IMEM[3] = 'b 1100_0100_0000_0000; // R4 = 0 DMEM address from
IMEM[4] = 'b 1100_0101_0000_0001; // R5 = 1 DMEM address from
IMEM[5] = 'b 1011_0110_0000_0100; // R6 = DMEM[R4=0] load;
IMEM[6] = 'b 1011_0111_0000_0101; // R7 = DMEM[R5=1] load;

IMEM[7] = 'b 1100_1000_0000_0001; // R8 = 1 for bit shift
IMEM[8] = 'b 1100_1001_0000_1100; // R9 = 12 loop return point
IMEM[9] = 'b 1100_1010_0000_1111; // R10 = 15 loop skip point
IMEM[10] = 'b 1100_1011_0001_0100; // R11 = 20 end point
IMEM[11] = 'b 1100_1100_0000_1000; // R12 = 8;

IMEM[12] = 'b 0101_1101_0101_0111; // R13 = R5 & R7
IMEM[13] = 'b 1001_0000_0000_1010; // to loop skip point
IMEM[14] = 'b 0000_0011_0011_0110; // R3 = R3+R6;
IMEM[15] = 'b 0011_0110_0110_1000; // R6 = R6<<R8(R8=1)
IMEM[16] = 'b 0011_0101_0101_1000; // R5 = R5<<R8(R8=1)
IMEM[17] = 'b 0001_1100_1100_1000; // R12 = R12-R8(R8=1);
IMEM[18] = 'b 1001_0000_0000_1011; // to end point
IMEM[19] = 'b 1000_0000_0000_1001; // to loop start
IMEM[20] = 'b 1100_1101_0000_0010; // R13 = 2 DMEM address to
IMEM[21] = 'b 1010_0000_0011_1101; // store R3 -> DMEM[R13=2]


end

always #10 CK = ~CK;

endmodule

5/cpu.vcd
$date
	Fri May 13 13:15:45 2022
$end
$version
	Icarus Verilog
$end
$timescale
	1s
$end
$scope module simcpu $end
$var wire 16 ! DD [15:0] $end
$var wire 1 " RW $end
$var wire 16 # IA [15:0] $end
$var wire 16 $ DA [15:0] $end
$var reg 1 % CK $end
$var reg 16 & DDi [15:0] $end
$var reg 16 ' ID [15:0] $end
$var reg 1 ( RST $end
$scope module c $end
$var wire 1 % CK $end
$var wire 16 ) DA [15:0] $end
$var wire 16 * DD [15:0] $end
$var wire 16 + IA [15:0] $end
$var wire 16 , ID [15:0] $end
$var wire 1 ( RST $end
$var wire 4 - OPR3 [3:0] $end
$var wire 4 . OPR2 [3:0] $end
$var wire 4 / OPR1 [3:0] $end
$var wire 4 0 OPCODE [3:0] $end
$var wire 8 1 IMM [7:0] $end
$var wire 16 2 CBUS [15:0] $end
$var wire 16 3 BBUS [15:0] $end
$var wire 16 4 ABUS [15:0] $end
$var reg 1 5 FLAG $end
$var reg 16 6 FUA [15:0] $end
$var reg 16 7 FUB [15:0] $end
$var reg 16 8 FUC [15:0] $end
$var reg 16 9 INST [15:0] $end
$var reg 16 : LSUA [15:0] $end
$var reg 16 ; LSUB [15:0] $end
$var reg 16 < LSUC [15:0] $end
$var reg 16 = PC [15:0] $end
$var reg 16 > PCC [15:0] $end
$var reg 16 ? PCI [15:0] $end
$var reg 1 " RW $end
$var reg 2 @ STAGE [1:0] $end
$upscope $end
$upscope $end
$enddefinitions $end
#0
$dumpvars
bx @
bx ?
bx >
bx =
bx <
bx ;
bx :
bx 9
bx 8
bx 7
bx 6
x5
bx 4
bx 3
bx 2
bx 1
bx 0
bx /
bx .
bx -
bx ,
bx +
bx *
bx )
0(
bx '
bx &
0%
bx $
bx #
x"
bx !
$end
#5
1(
#10
1"
b0 @
b0 #
b0 +
b0 =
1%
#20
b1100000000000000 '
b1100000000000000 ,
0%
#30
1%
#40
0%
#50
1%
#60
0%
#70
1%
#80
0%
#90
1%
#100
0%
#105
0(
#110
b0 2
b0 4
b0 3
b1100 0
b0 /
b0 .
b0 -
b0 1
b1100000000000000 9
b1 @
1%
#120
0%
#130
b1 ?
b10 @
1%
#140
0%
#150
b11 @
1%
#160
0%
#170
b1 #
b1 +
b1 =
b0 @
1%
#180
b1100000100000001 '
b1100000100000001 ,
0%
#190
b1 2
bx 3
b1 /
b1 -
b1 1
b1100000100000001 9
b1 @
1%
#200
0%
#210
b10 ?
b10 @
1%
#220
0%
#230
b11 @
1%
#240
0%
#250
b1 3
b10 #
b10 +
b10 =
b0 @
1%
#260
b1100001000000010 '
b1100001000000010 ,
0%
#270
b10 2
bx 3
b10 /
b10 -
b10 1
b1100001000000010 9
b1 @
1%
#280
0%
#290
b11 ?
b10 @
1%
#300
0%
#310
b11 @
1%
#320
0%
#330
b10 3
b11 #
b11 +
b11 =
b0 @
1%
#340
b1100001100000011 '
b1100001100000011 ,
0%
#350
b11 2
bx 3
b11 /
b11 -
b11 1
b1100001100000011 9
b1 @
1%
#360
0%
#370
b100 ?
b10 @
1%
#380
0%
#390
b11 @
1%
#400
0%
#410
b11 3
b100 #
b100 +
b100 =
b0 @
1%
#420
b1100010000000100 '
b1100010000000100 ,
0%
#430
b100 2
bx 3
b100 /
b100 -
b100 1
b1100010000000100 9
b1 @
1%
#440
0%
#450
b101 ?
b10 @
1%
#460
0%
#470
b11 @
1%
#480
0%
#490
b100 3
b101 #
b101 +
b101 =
b0 @
1%
#500
b10100010011 '
b10100010011 ,
0%
#510
bx 2
b1 4
b11 3
b0 0
b101 /
b1 .
b11 -
b10011 1
b10100010011 9
b1 @
1%
#520
0%
#530
b110 ?
b11 7
b1 6
b10 @
1%
#540
0%
#550
b100 2
b100 8
b11 @
1%
#560
0%
#570
05
b110 #
b110 +
b110 =
b0 @
1%
#580
b1010000001010000 '
b1010000001010000 ,
0%
#590
bx 2
b100 4
b0 3
b1010 0
b0 /
b101 .
b0 -
b1010000 1
b1010000001010000 9
b1 @
1%
#600
0%
#610
b111 ?
b0 $
b0 )
b0 ;
b100 :
b10 @
1%
#620
0%
#630
b100 !
b100 *
0"
b11 @
1%
